{"name":"build-javascript","namedChunkGroups":{"app":{"name":"app","assets":[{"name":"webpack-runtime-c7cbaf23a8a482465a88.js","size":4071},{"name":"framework-695947703815c1a838cc.js","size":140946},{"name":"styles.e67ecf36d1b559deb180.css","size":10448},{"name":"app-d4e417bc1390c1b4a1d4.js","size":61268}],"filteredAssets":0,"assetsSize":216733,"filteredAuxiliaryAssets":3,"auxiliaryAssetsSize":591085},"component---src-pages-404-jsx":{"name":"component---src-pages-404-jsx","assets":[{"name":"commons-bc1077c94498daf0f9b9.js","size":18685},{"name":"component---src-pages-404-jsx-f2007a02fceca49eb0fb.js","size":824}],"filteredAssets":0,"assetsSize":19509,"filteredAuxiliaryAssets":2,"auxiliaryAssetsSize":80963},"component---src-pages-about-jsx":{"name":"component---src-pages-about-jsx","assets":[{"name":"framework-695947703815c1a838cc.js","size":140946},{"name":"commons-bc1077c94498daf0f9b9.js","size":18685},{"name":"component---src-pages-about-jsx-09b58cff039ac3cf8b3b.js","size":122992}],"filteredAssets":0,"assetsSize":282623,"filteredAuxiliaryAssets":3,"auxiliaryAssetsSize":1071549},"component---src-pages-index-jsx":{"name":"component---src-pages-index-jsx","assets":[{"name":"commons-bc1077c94498daf0f9b9.js","size":18685},{"name":"component---src-pages-index-jsx-acb79e24257545058286.js","size":1297}],"filteredAssets":0,"assetsSize":19982,"filteredAuxiliaryAssets":2,"auxiliaryAssetsSize":81555},"component---src-pages-leadership-jsx":{"name":"component---src-pages-leadership-jsx","assets":[{"name":"commons-bc1077c94498daf0f9b9.js","size":18685},{"name":"component---src-pages-leadership-jsx-fc5817126b1d1f8fb338.js","size":6085}],"filteredAssets":0,"assetsSize":24770,"filteredAuxiliaryAssets":2,"auxiliaryAssetsSize":89223},"component---src-pages-projects-jsx":{"name":"component---src-pages-projects-jsx","assets":[{"name":"commons-bc1077c94498daf0f9b9.js","size":18685},{"name":"component---src-pages-projects-jsx-8a850419836c1cc6dcd0.js","size":5147}],"filteredAssets":0,"assetsSize":23832,"filteredAuxiliaryAssets":2,"auxiliaryAssetsSize":87195},"component---src-pages-resume-jsx":{"name":"component---src-pages-resume-jsx","assets":[{"name":"commons-bc1077c94498daf0f9b9.js","size":18685},{"name":"component---src-pages-resume-jsx-c4cf015d2598e21afef5.js","size":2733}],"filteredAssets":0,"assetsSize":21418,"filteredAuxiliaryAssets":2,"auxiliaryAssetsSize":85836}},"assetsByChunkName":{"app":["webpack-runtime-c7cbaf23a8a482465a88.js","framework-695947703815c1a838cc.js","styles.e67ecf36d1b559deb180.css","app-d4e417bc1390c1b4a1d4.js"],"component---src-pages-404-jsx":["commons-bc1077c94498daf0f9b9.js","component---src-pages-404-jsx-f2007a02fceca49eb0fb.js"],"component---src-pages-about-jsx":["framework-695947703815c1a838cc.js","commons-bc1077c94498daf0f9b9.js","component---src-pages-about-jsx-09b58cff039ac3cf8b3b.js"],"component---src-pages-index-jsx":["commons-bc1077c94498daf0f9b9.js","component---src-pages-index-jsx-acb79e24257545058286.js"],"component---src-pages-leadership-jsx":["commons-bc1077c94498daf0f9b9.js","component---src-pages-leadership-jsx-fc5817126b1d1f8fb338.js"],"component---src-pages-projects-jsx":["commons-bc1077c94498daf0f9b9.js","component---src-pages-projects-jsx-8a850419836c1cc6dcd0.js"],"component---src-pages-resume-jsx":["commons-bc1077c94498daf0f9b9.js","component---src-pages-resume-jsx-c4cf015d2598e21afef5.js"]},"childAssetsByChunkName":{}}